__init__.py
examples/conversation_bot_1.py
examples/conversation_bot_2.py
examples/echo_bot.py
examples/reply_interactive_message_bot.py
examples/reply_message_bot.py
examples/send_interactive_message.py
examples/send_simple_message.py
examples/send_template_message.py
python_whatsapp_bot/__init__.py
python_whatsapp_bot/dispatcher.py
python_whatsapp_bot/error_handlers.py
python_whatsapp_bot/handler_classes.py
python_whatsapp_bot/markup.py
python_whatsapp_bot/message.py
python_whatsapp_bot/py.typed
python_whatsapp_bot/user_context.py
python_whatsapp_bot/whatsapp.py
python_whatsapp_bot-2.0.3.dist-info/licenses/LICENSE
python_whatsapp_bot-2.0.3.dist-info/METADATA
python_whatsapp_bot-2.0.3.dist-info/WHEEL
python_whatsapp_bot-2.0.3.dist-info/top_level.txt
python_whatsapp_bot-2.0.3.dist-info/RECORD
