Metadata-Version: 2.4
Name: python-whatsapp-bot
Version: 2.0.3
Summary: A whatsapp client library for python using the new WhatsApp cloud API
Author-email: Radi <evaradi18@gmail.com>
License: MIT License
Project-URL: Homepage, https://github.com/Radi-dev/python-whatsapp-cloud-bot
Project-URL: Bug Tracker, https://github.com/Radi-dev/python-whatsapp-cloud-bot/issues
Classifier: Programming Language :: Python :: 3
Classifier: License :: OSI Approved :: MIT License
Classifier: Operating System :: OS Independent
Requires-Python: >=3.7
License-File: LICENSE
Requires-Dist: requests>=2
Dynamic: license-file
